[
    {
        "id":1,
        "nombre":"Jose",
        "apellido":"Velastegui",
        "correo":"jo@gmail.com",
        "fechaNacimiento":"2000-06-08",
        "estado":"Activo"
    },
    {
        "id":2,
        "nombre":"Maria",
        "apellido":"Velastegui",
        "correo":"jo@gmail.com",
        "fechaNacimiento":"2000-06-08",
        "estado":"Activo"
    },
    {
        "id":3,
        "nombre":"Josefina",
        "apellido":"Velastegui",
        "correo":"jo@gmail.com",
        "fechaNacimiento":"2000-06-08",
        "estado":"Activo"
    },
    {
        "id":4,
        "nombre":"Israel",
        "apellido":"Velastegui",
        "correo":"jo@gmail.com",
        "fechaNacimiento":"2000-06-08",
        "estado":"Activo"
    },
    {
        "id":5,
        "nombre":"Mario",
        "apellido":"Velastegui",
        "correo":"jo@gmail.com",
        "fechaNacimiento":"2000-06-08",
        "estado":"Activo"
    },
    {
        "id":6,
        "nombre":"Martha",
        "apellido":"Velastegui",
        "correo":"jo@gmail.com",
        "fechaNacimiento":"2000-06-08",
        "estado":"Activo"
    },
    {
        "id":7,
        "nombre":"Milly",
        "apellido":"Velastegui",
        "correo":"jo@gmail.com",
        "fechaNacimiento":"2000-06-08",
        "estado":"Activo"
    },
    {
        "id":8,
        "nombre":"Mariluz",
        "apellido":"Velastegui",
        "correo":"jo@gmail.com",
        "fechaNacimiento":"2000-06-08",
        "estado":"Activo"
    },
    {
        "id":9,
        "nombre":"David",
        "apellido":"Velastegui",
        "correo":"jo@gmail.com",
        "fechaNacimiento":"2000-06-08",
        "estado":"Activo"
    },
    {
        "id":10,
        "nombre":"Daniel",
        "apellido":"Velastegui",
        "correo":"jo@gmail.com",
        "fechaNacimiento":"2000-06-08",
        "estado":"Activo"
    },
    {
        "id":11,
        "nombre":"Kevin",
        "apellido":"Velastegui",
        "correo":"jo@gmail.com",
        "fechaNacimiento":"2000-06-08",
        "estado":"Activo"
    },
    {
        "id":12,
        "nombre":"Carlos",
        "apellido":"Velastegui",
        "correo":"jo@gmail.com",
        "fechaNacimiento":"2000-06-08",
        "estado":"Activo"
    },
    {
        "id":13,
        "nombre":"Josefa",
        "apellido":"Velastegui",
        "correo":"jo@gmail.com",
        "fechaNacimiento":"2000-06-08",
        "estado":"Activo"
    },
    {
        "id":14,
        "nombre":"Estefania",
        "apellido":"Velastegui",
        "correo":"jo@gmail.com",
        "fechaNacimiento":"2000-06-08",
        "estado":"Activo"
    }
]